tce/__init__.py
tce/__main__.py
tce/tce.css
tce/tce.py
tce-0.0.1.data/data/tce.css
tce-0.0.1.dist-info/LICENSE
tce-0.0.1.dist-info/METADATA
tce-0.0.1.dist-info/WHEEL
tce-0.0.1.dist-info/entry_points.txt
tce-0.0.1.dist-info/top_level.txt
tce-0.0.1.dist-info/RECORD
